nemo_run/__init__.py
nemo_run/__main__.py
nemo_run/api.py
nemo_run/config.py
nemo_run/exceptions.py
nemo_run/help.py
nemo_run/package_info.py
nemo_run/cli/__init__.py
nemo_run/cli/api.py
nemo_run/cli/cli_parser.py
nemo_run/cli/config.py
nemo_run/cli/devspace.py
nemo_run/cli/experiment.py
nemo_run/cli/lazy.py
nemo_run/cli/workspace.py
nemo_run/core/__init__.py
nemo_run/core/execution/__init__.py
nemo_run/core/execution/base.py
nemo_run/core/execution/dgxcloud.py
nemo_run/core/execution/docker.py
nemo_run/core/execution/kuberay.py
nemo_run/core/execution/launcher.py
nemo_run/core/execution/lepton.py
nemo_run/core/execution/local.py
nemo_run/core/execution/skypilot.py
nemo_run/core/execution/skypilot_jobs.py
nemo_run/core/execution/slurm.py
nemo_run/core/execution/utils.py
nemo_run/core/execution/templates/ft_launcher.j2
nemo_run/core/execution/templates/slurm.sh.j2
nemo_run/core/execution/templates/slurm_ray.sh.j2
nemo_run/core/frontend/__init__.py
nemo_run/core/frontend/console/__init__.py
nemo_run/core/frontend/console/api.py
nemo_run/core/frontend/console/styles.py
nemo_run/core/packaging/__init__.py
nemo_run/core/packaging/base.py
nemo_run/core/packaging/git.py
nemo_run/core/packaging/hybrid.py
nemo_run/core/packaging/pattern.py
nemo_run/core/runners/__init__.py
nemo_run/core/runners/fdl_runner.py
nemo_run/core/serialization/__init__.py
nemo_run/core/serialization/yaml.py
nemo_run/core/serialization/zlib_json.py
nemo_run/core/tunnel/__init__.py
nemo_run/core/tunnel/client.py
nemo_run/core/tunnel/rsync.py
nemo_run/core/tunnel/server.py
nemo_run/devspace/__init__.py
nemo_run/devspace/base.py
nemo_run/devspace/editor.py
nemo_run/run/__init__.py
nemo_run/run/api.py
nemo_run/run/experiment.py
nemo_run/run/job.py
nemo_run/run/logs.py
nemo_run/run/plugin.py
nemo_run/run/task.py
nemo_run/run/utils.py
nemo_run/run/ray/__init__.py
nemo_run/run/ray/cluster.py
nemo_run/run/ray/job.py
nemo_run/run/ray/kuberay.py
nemo_run/run/ray/slurm.py
nemo_run/run/ray/templates/ray.sub.j2
nemo_run-0.7.0.dist-info/METADATA
nemo_run-0.7.0.dist-info/WHEEL
nemo_run-0.7.0.dist-info/entry_points.txt
nemo_run-0.7.0.dist-info/licenses/LICENSE
nemo_run-0.7.0.dist-info/RECORD
