Metadata-Version: 2.4
Name: nemo_run
Version: 0.7.0
Summary: A powerful tool designed to streamline the configuration, execution and management of Machine Learning experiments across various computing environments.
License-File: LICENSE
Requires-Python: >=3.10
Requires-Dist: catalogue>=2.0.10
Requires-Dist: cryptography<43.0.0
Requires-Dist: fabric>=3.2.2
Requires-Dist: fiddle>=0.3.0
Requires-Dist: inquirerpy>=0.3.4
Requires-Dist: jinja2>=3.1.4
Requires-Dist: leptonai>=0.25.0
Requires-Dist: networkx>=3.3
Requires-Dist: omegaconf>=2.3.0
Requires-Dist: packaging
Requires-Dist: rich>=13.7.1
Requires-Dist: toml
Requires-Dist: torchx>=0.7.0
Requires-Dist: typer>=0.12.3
Provides-Extra: ray
Requires-Dist: kubernetes; extra == 'ray'
Provides-Extra: skypilot
Requires-Dist: skypilot[kubernetes]>=0.10.0; extra == 'skypilot'
Provides-Extra: skypilot-all
Requires-Dist: skypilot[all]>=0.10.0; extra == 'skypilot-all'
